color_thief_fast.py
color_thief_fast-1.0.3.dist-info/METADATA
color_thief_fast-1.0.3.dist-info/WHEEL
color_thief_fast-1.0.3.dist-info/top_level.txt
color_thief_fast-1.0.3.dist-info/RECORD
