Metadata-Version: 2.2
Name: color_thief_fast
Version: 1.0.3
Summary: extracting image theme colors
Author-email: Jianglong Jia <465710779@qq.com>
Project-URL: Homepage, https://github.com/jjl001/color_thief_fast
Classifier: Development Status :: 3 - Alpha
Classifier: Programming Language :: Python :: 3
Classifier: License :: OSI Approved :: MIT License
Classifier: Operating System :: OS Independent
Requires-Python: >=3.8
Requires-Dist: Pillow
Requires-Dist: numpy
